jinja_gen
