Metadata-Version: 2.1
Name: jinja-gen
Version: 1.3.2
Summary: Generate script files from easy configs
Home-page: https://github.com/activatedgeek/jinja_gen
Author: Sanyam Kapoor
License: MIT
Platform: UNKNOWN
Classifier: Programming Language :: Python :: 3.6
Classifier: Development Status :: 5 - Production/Stable
Classifier: Intended Audience :: Developers
Classifier: Topic :: Software Development
Classifier: Topic :: Software Development :: Pre-processors
Classifier: Topic :: Software Development :: Libraries :: Python Modules
Classifier: Topic :: Utilities
Classifier: License :: OSI Approved :: MIT License
